bscan/__init__.py
bscan/__main__.py
bscan/cli.py
bscan/cli_shells.py
bscan/cli_wordlists.py
bscan/config.py
bscan/dir_gen.py
bscan/dir_structure.py
bscan/errors.py
bscan/io_console.py
bscan/io_files.py
bscan/models.py
bscan/networks.py
bscan/runtime.py
bscan/scans.py
bscan/shells.py
bscan/version.py
bscan/wordlists.py
bscan/configuration/patterns.txt
bscan/configuration/port-scans.toml
bscan/configuration/required-programs.txt
bscan/configuration/reverse-shells.toml
bscan/configuration/service-scans.toml
bscan-0.1.4.dist-info/LICENSE.txt
bscan-0.1.4.dist-info/METADATA
bscan-0.1.4.dist-info/WHEEL
bscan-0.1.4.dist-info/entry_points.txt
bscan-0.1.4.dist-info/top_level.txt
bscan-0.1.4.dist-info/RECORD
