Metadata-Version: 2.1
Name: bscan
Version: 0.1.4
Summary: An asynchronous target scanner
Home-page: https://github.com/welchbj/bscan
Author: Brian Welch
Author-email: welch18@vt.edu
License: MIT
Platform: UNKNOWN
Classifier: Environment :: Console
Classifier: License :: OSI Approved :: MIT License
Classifier: Operating System :: POSIX
Classifier: Programming Language :: Python :: 3.6
Classifier: Topic :: Utilities
Requires-Dist: colorama
Requires-Dist: sublemon
Requires-Dist: toml
